[{"started_at": "2023-03-18T12:12:01.974000", "duration": "0:00:00.033411", "query": "INSERT INTO amit.barak (dgqx, relf, cgju) VALUES('wsk', 'kqu', 'jwt') USING TIMESTAMP 1;"}, {"started_at": "2023-03-18T12:12:01.974000", "duration": "0:00:00.033619", "query": "INSERT INTO amit.barak (dgqx, relf, cgju) VALUES('xbs', 'zoa', 'gis') USING TIMESTAMP 2;"}, {"started_at": "2023-03-18T12:12:01.983000", "duration": "0:00:00.032801", "query": "INSERT INTO amit.barak (dgqx, relf, cgju) VALUES('nyl', 'bzx', 'evp') USING TIMESTAMP 3;"}, {"started_at": "2023-03-18T12:12:01.988000", "duration": "0:00:00.038947", "query": "INSERT INTO amit.barak (dgqx, relf, cgju) VALUES('hti', 'ggh', 'hvw') USING TIMESTAMP 4;"}, {"started_at": "2023-03-18T12:12:02.002000", "duration": "0:00:00.025129", "query": "INSERT INTO amit.barak (dgqx, relf, cgju) VALUES('tsk', 'wiv', 'fdx') USING TIMESTAMP 5;"}, {"started_at": "2023-03-18T12:12:02.003000", "duration": "0:00:00.034281", "query": "INSERT INTO amit.barak (dgqx, relf, cgju) VALUES('caj', 'skh', 'hpu') USING TIMESTAMP 6;"}, {"started_at": "2023-03-18T12:12:02.002000", "duration": "0:00:00.038965", "query": "INSERT INTO amit.barak (dgqx, relf, cgju) VALUES('lpt', 'lvu', 'jpl') USING TIMESTAMP 7;"}, {"started_at": "2023-03-18T12:12:02.003000", "duration": "0:00:00.033830", "query": "INSERT INTO amit.barak (dgqx, relf, cgju) VALUES('lra', 'uei', 'ycf') USING TIMESTAMP 8;"}, {"started_at": "2023-03-18T12:12:02.003000", "duration": "0:00:00.038668", "query": "INSERT INTO amit.barak (dgqx, relf, cgju) VALUES('zle', 'jzb', 'akd') USING TIMESTAMP 9;"}, {"started_at": "2023-03-18T12:12:02.003000", "duration": "0:00:00.023201", "query": "INSERT INTO amit.barak (dgqx, relf, cgju) VALUES('keh', 'nux', 'gzm') USING TIMESTAMP 10;"}, {"started_at": "2023-03-18T12:12:02.016000", "duration": "0:00:00.025384", "query": "INSERT INTO amit.barak (dgqx, relf, cgju) VALUES('hij', 'jct', 'zox') USING TIMESTAMP 11;"}, {"started_at": "2023-03-18T12:12:02.018000", "duration": "0:00:00.023402", "query": "INSERT INTO amit.barak (dgqx, relf, cgju) VALUES('fyq', 'oho', 'wfg') USING TIMESTAMP 12;"}, {"started_at": "2023-03-18T12:12:02.024000", "duration": "0:00:00.019638", "query": "INSERT INTO amit.barak (dgqx, relf, cgju) VALUES('xly', 'lgo', 'jab') USING TIMESTAMP 13;"}, {"started_at": "2023-03-18T12:12:02.031000", "duration": "0:00:00.012356", "query": "INSERT INTO amit.barak (dgqx, relf, cgju) VALUES('xgy', 'cvo', 'khp') USING TIMESTAMP 14;"}, {"started_at": "2023-03-18T12:12:02.030000", "duration": "0:00:00.013633", "query": "INSERT INTO amit.barak (dgqx, relf, cgju) VALUES('uyf', 'juw', 'vee') USING TIMESTAMP 15;"}, {"started_at": "2023-03-18T12:12:02.033000", "duration": "0:00:00.011622", "query": "INSERT INTO amit.barak (dgqx, relf, cgju) VALUES('msg', 'xvl', 'zom') USING TIMESTAMP 16;"}, {"started_at": "2023-03-18T12:12:02.051000", "duration": "0:00:00.006597", "query": "INSERT INTO amit.barak (dgqx, relf, cgju) VALUES('uwe', 'jir', 'pfo') USING TIMESTAMP 17;"}, {"started_at": "2023-03-18T12:12:02.051000", "duration": "0:00:00.005279", "query": "INSERT INTO amit.barak (dgqx, relf, cgju) VALUES('zlx', 'nph', 'yqj') USING TIMESTAMP 18;"}, {"started_at": "2023-03-18T12:12:02.051000", "duration": "0:00:00.006652", "query": "INSERT INTO amit.barak (dgqx, relf, cgju) VALUES('tnw', 'dyu', 'ixb') USING TIMESTAMP 19;"}, {"started_at": "2023-03-18T12:12:02.051000", "duration": "0:00:00.005648", "query": "INSERT INTO amit.barak (dgqx, relf, cgju) VALUES('zsh', 'irm', 'zfn') USING TIMESTAMP 20;"}, {"started_at": "2023-03-18T12:12:02.052000", "duration": "0:00:00.008628", "query": "INSERT INTO amit.barak (dgqx, relf, cgju) VALUES('nit', 'cog', 'mbj') USING TIMESTAMP 21;"}, {"started_at": "2023-03-18T12:12:02.052000", "duration": "0:00:00.004785", "query": "INSERT INTO amit.barak (dgqx, relf, cgju) VALUES('mbe', 'jeo', 'ijy') USING TIMESTAMP 22;"}, {"started_at": "2023-03-18T12:12:02.052000", "duration": "0:00:00.005448", "query": "INSERT INTO amit.barak (dgqx, relf, cgju) VALUES('raj', 'uun', 'jul') USING TIMESTAMP 23;"}, {"started_at": "2023-03-18T12:12:02.052000", "duration": "0:00:00.005400", "query": "INSERT INTO amit.barak (dgqx, relf, cgju) VALUES('ciu', 'cpk', 'hic') USING TIMESTAMP 24;"}, {"started_at": "2023-03-18T12:12:02.053000", "duration": "0:00:00.008023", "query": "INSERT INTO amit.barak (dgqx, relf, cgju) VALUES('luz', 'gzb', 'xfk') USING TIMESTAMP 25;"}, {"started_at": "2023-03-18T12:12:02.053000", "duration": "0:00:00.004795", "query": "INSERT INTO amit.barak (dgqx, relf, cgju) VALUES('kio', 'cwy', 'tom') USING TIMESTAMP 26;"}, {"started_at": "2023-03-18T12:12:02.061000", "duration": "0:00:00.007162", "query": "INSERT INTO amit.barak (dgqx, relf, cgju) VALUES('zvn', 'dmk', 'cqu') USING TIMESTAMP 27;"}, {"started_at": "2023-03-18T12:12:02.061000", "duration": "0:00:00.006364", "query": "INSERT INTO amit.barak (dgqx, relf, cgju) VALUES('fpi', 'wqh', 'qnx') USING TIMESTAMP 28;"}, {"started_at": "2023-03-18T12:12:02.061000", "duration": "0:00:00.005922", "query": "INSERT INTO amit.barak (dgqx, relf, cgju) VALUES('hod', 'spn', 'dhs') USING TIMESTAMP 29;"}, {"started_at": "2023-03-18T12:12:02.062000", "duration": "0:00:00.005432", "query": "INSERT INTO amit.barak (dgqx, relf, cgju) VALUES('ccz', 'qsy', 'ipz') USING TIMESTAMP 30;"}, {"started_at": "2023-03-18T12:12:02.061000", "duration": "0:00:00.005962", "query": "INSERT INTO amit.barak (dgqx, relf, cgju) VALUES('srb', 'apo', 'lnj') USING TIMESTAMP 31;"}, {"started_at": "2023-03-18T12:12:02.061000", "duration": "0:00:00.008108", "query": "INSERT INTO amit.barak (dgqx, relf, cgju) VALUES('nbx', 'vax', 'jrw') USING TIMESTAMP 32;"}, {"started_at": "2023-03-18T12:12:02.062000", "duration": "0:00:00.005228", "query": "INSERT INTO amit.barak (dgqx, relf, cgju) VALUES('pvm', 'ckm', 'gds') USING TIMESTAMP 33;"}, {"started_at": "2023-03-18T12:12:02.062000", "duration": "0:00:00.005281", "query": "INSERT INTO amit.barak (dgqx, relf, cgju) VALUES('zok', 'eku', 'ytz') USING TIMESTAMP 34;"}, {"started_at": "2023-03-18T12:12:02.070000", "duration": "0:00:00.007828", "query": "INSERT INTO amit.barak (dgqx, relf, cgju) VALUES('oxb', 'uzz', 'wst') USING TIMESTAMP 35;"}, {"started_at": "2023-03-18T12:12:02.070000", "duration": "0:00:00.006726", "query": "INSERT INTO amit.barak (dgqx, relf, cgju) VALUES('wvc', 'cfw', 'pfz') USING TIMESTAMP 36;"}, {"started_at": "2023-03-18T12:12:02.072000", "duration": "0:00:00.012740", "query": "INSERT INTO amit.barak (dgqx, relf, cgju) VALUES('zfy', 'rzc', 'xfb') USING TIMESTAMP 37;"}, {"started_at": "2023-03-18T12:12:02.072000", "duration": "0:00:00.012510", "query": "INSERT INTO amit.barak (dgqx, relf, cgju) VALUES('xpq', 'dyn', 'usk') USING TIMESTAMP 38;"}, {"started_at": "2023-03-18T12:12:02.073000", "duration": "0:00:00.015583", "query": "INSERT INTO amit.barak (dgqx, relf, cgju) VALUES('ihb', 'hza', 'xgb') USING TIMESTAMP 39;"}, {"started_at": "2023-03-18T12:12:02.073000", "duration": "0:00:00.011821", "query": "INSERT INTO amit.barak (dgqx, relf, cgju) VALUES('xaf', 'eam', 'cah') USING TIMESTAMP 40;"}, {"started_at": "2023-03-18T12:12:02.074000", "duration": "0:00:00.011448", "query": "UPDATE amit.barak USING TIMESTAMP 41 SET relf = 'mzt' WHERE dgqx = 'wsk';"}, {"started_at": "2023-03-18T12:12:02.074000", "duration": "0:00:00.011240", "query": "UPDATE amit.barak USING TIMESTAMP 42 SET relf = 'dca' WHERE dgqx = 'mzt';"}, {"started_at": "2023-03-18T12:12:02.074000", "duration": "0:00:00.010796", "query": "UPDATE amit.barak USING TIMESTAMP 43 SET relf = 'nio' WHERE dgqx = 'dca';"}, {"started_at": "2023-03-18T12:12:02.075000", "duration": "0:00:00.010288", "query": "UPDATE amit.barak USING TIMESTAMP 44 SET relf = 'ame' WHERE dgqx = 'nio';"}, {"started_at": "2023-03-18T12:12:02.078000", "duration": "0:00:00.007314", "query": "UPDATE amit.barak USING TIMESTAMP 45 SET relf = 'sfq' WHERE dgqx = 'ame';"}, {"started_at": "2023-03-18T12:12:02.079000", "duration": "0:00:00.006545", "query": "UPDATE amit.barak USING TIMESTAMP 46 SET relf = 'ovx' WHERE dgqx = 'sfq';"}, {"started_at": "2023-03-18T12:12:02.088000", "duration": "0:00:00.007142", "query": "UPDATE amit.barak USING TIMESTAMP 47 SET relf = 'ovq' WHERE dgqx = 'ovx';"}, {"started_at": "2023-03-18T12:12:02.088000", "duration": "0:00:00.006668", "query": "UPDATE amit.barak USING TIMESTAMP 48 SET relf = 'mse' WHERE dgqx = 'ovq';"}, {"started_at": "2023-03-18T12:12:02.088000", "duration": "0:00:00.007156", "query": "UPDATE amit.barak USING TIMESTAMP 49 SET relf = 'jet' WHERE dgqx = 'mse';"}, {"started_at": "2023-03-18T12:12:02.088000", "duration": "0:00:00.007063", "query": "UPDATE amit.barak USING TIMESTAMP 50 SET relf = 'swh' WHERE dgqx = 'jet';"}, {"started_at": "2023-03-18T12:12:02.088000", "duration": "0:00:00.006489", "query": "UPDATE amit.barak USING TIMESTAMP 51 SET relf = 'iik' WHERE dgqx = 'swh';"}, {"started_at": "2023-03-18T12:12:02.088000", "duration": "0:00:00.006969", "query": "UPDATE amit.barak USING TIMESTAMP 52 SET relf = 'rxy' WHERE dgqx = 'iik';"}, {"started_at": "2023-03-18T12:12:02.089000", "duration": "0:00:00.006422", "query": "UPDATE amit.barak USING TIMESTAMP 53 SET relf = 'cay' WHERE dgqx = 'rxy';"}, {"started_at": "2023-03-18T12:12:02.089000", "duration": "0:00:00.006151", "query": "UPDATE amit.barak USING TIMESTAMP 54 SET relf = 'qkb' WHERE dgqx = 'cay';"}, {"started_at": "2023-03-18T12:12:02.089000", "duration": "0:00:00.005880", "query": "UPDATE amit.barak USING TIMESTAMP 55 SET relf = 'qos' WHERE dgqx = 'qkb';"}, {"started_at": "2023-03-18T12:12:02.091000", "duration": "0:00:00.004440", "query": "UPDATE amit.barak USING TIMESTAMP 56 SET relf = 'rej' WHERE dgqx = 'qos';"}, {"started_at": "2023-03-18T12:12:02.097000", "duration": "0:00:00.003881", "query": "UPDATE amit.barak USING TIMESTAMP 57 SET relf = 'nis' WHERE dgqx = 'rej';"}, {"started_at": "2023-03-18T12:12:02.097000", "duration": "0:00:00.004502", "query": "UPDATE amit.barak USING TIMESTAMP 58 SET relf = 'atl' WHERE dgqx = 'nis';"}, {"started_at": "2023-03-18T12:12:02.097000", "duration": "0:00:00.004292", "query": "UPDATE amit.barak USING TIMESTAMP 59 SET relf = 'fxu' WHERE dgqx = 'atl';"}, {"started_at": "2023-03-18T12:12:02.097000", "duration": "0:00:00.003975", "query": "UPDATE amit.barak USING TIMESTAMP 60 SET relf = 'ftv' WHERE dgqx = 'fxu';"}, {"started_at": "2023-03-18T12:12:02.098000", "duration": "0:00:00.003491", "query": "UPDATE amit.barak USING TIMESTAMP 61 SET relf = 'gvu' WHERE dgqx = 'ftv';"}, {"started_at": "2023-03-18T12:12:02.097000", "duration": "0:00:00.003379", "query": "UPDATE amit.barak USING TIMESTAMP 62 SET relf = 'ksd' WHERE dgqx = 'gvu';"}, {"started_at": "2023-03-18T12:12:02.097000", "duration": "0:00:00.003162", "query": "UPDATE amit.barak USING TIMESTAMP 63 SET relf = 'qey' WHERE dgqx = 'ksd';"}, {"started_at": "2023-03-18T12:12:02.097000", "duration": "0:00:00.003182", "query": "UPDATE amit.barak USING TIMESTAMP 64 SET relf = 'wgq' WHERE dgqx = 'qey';"}, {"started_at": "2023-03-18T12:12:02.098000", "duration": "0:00:00.003051", "query": "UPDATE amit.barak USING TIMESTAMP 65 SET relf = 'tlf' WHERE dgqx = 'wgq';"}, {"started_at": "2023-03-18T12:12:02.098000", "duration": "0:00:00.003181", "query": "UPDATE amit.barak USING TIMESTAMP 66 SET relf = 'yfl' WHERE dgqx = 'tlf';"}, {"started_at": "2023-03-18T12:12:02.104000", "duration": "0:00:00.004944", "query": "UPDATE amit.barak USING TIMESTAMP 67 SET relf = 'fit' WHERE dgqx = 'yfl';"}, {"started_at": "2023-03-18T12:12:02.104000", "duration": "0:00:00.005301", "query": "UPDATE amit.barak USING TIMESTAMP 68 SET relf = 'xkk' WHERE dgqx = 'fit';"}, {"started_at": "2023-03-18T12:12:02.104000", "duration": "0:00:00.004591", "query": "UPDATE amit.barak USING TIMESTAMP 69 SET relf = 'xvy' WHERE dgqx = 'xkk';"}, {"started_at": "2023-03-18T12:12:02.104000", "duration": "0:00:00.005238", "query": "UPDATE amit.barak USING TIMESTAMP 70 SET relf = 'vru' WHERE dgqx = 'xvy';"}, {"started_at": "2023-03-18T12:12:02.104000", "duration": "0:00:00.004098", "query": "UPDATE amit.barak USING TIMESTAMP 71 SET relf = 'ozn' WHERE dgqx = 'vru';"}, {"started_at": "2023-03-18T12:12:02.104000", "duration": "0:00:00.004072", "query": "UPDATE amit.barak USING TIMESTAMP 72 SET relf = 'xno' WHERE dgqx = 'ozn';"}, {"started_at": "2023-03-18T12:12:02.104000", "duration": "0:00:00.004015", "query": "UPDATE amit.barak USING TIMESTAMP 73 SET relf = 'gyi' WHERE dgqx = 'xno';"}, {"started_at": "2023-03-18T12:12:02.105000", "duration": "0:00:00.004027", "query": "UPDATE amit.barak USING TIMESTAMP 74 SET relf = 'zyb' WHERE dgqx = 'gyi';"}, {"started_at": "2023-03-18T12:12:02.105000", "duration": "0:00:00.003906", "query": "UPDATE amit.barak USING TIMESTAMP 75 SET relf = 'mqu' WHERE dgqx = 'zyb';"}, {"started_at": "2023-03-18T12:12:02.105000", "duration": "0:00:00.004232", "query": "UPDATE amit.barak USING TIMESTAMP 76 SET relf = 'nmo' WHERE dgqx = 'mqu';"}, {"started_at": "2023-03-18T12:12:02.111000", "duration": "0:00:00.006916", "query": "UPDATE amit.barak USING TIMESTAMP 77 SET relf = 'amy' WHERE dgqx = 'nmo';"}, {"started_at": "2023-03-18T12:12:02.111000", "duration": "0:00:00.006387", "query": "UPDATE amit.barak USING TIMESTAMP 78 SET relf = 'lzx' WHERE dgqx = 'amy';"}, {"started_at": "2023-03-18T12:12:02.111000", "duration": "0:00:00.006308", "query": "UPDATE amit.barak USING TIMESTAMP 79 SET relf = 'lrk' WHERE dgqx = 'lzx';"}, {"started_at": "2023-03-18T12:12:02.112000", "duration": "0:00:00.006696", "query": "UPDATE amit.barak USING TIMESTAMP 80 SET relf = 'bxz' WHERE dgqx = 'lrk';"}, {"started_at": "2023-03-18T12:12:02.112000", "duration": "0:00:00.006202", "query": "DELETE FROM amit.barak USING TIMESTAMP 81 WHERE dgqx='bxz';"}, {"started_at": "2023-03-18T12:12:02.112000", "duration": "0:00:00.006397", "query": "DELETE FROM amit.barak USING TIMESTAMP 82 WHERE dgqx='xbs';"}, {"started_at": "2023-03-18T12:12:02.112000", "duration": "0:00:00.005758", "query": "DELETE FROM amit.barak USING TIMESTAMP 83 WHERE dgqx='nyl';"}, {"started_at": "2023-03-18T12:12:02.112000", "duration": "0:00:00.006775", "query": "DELETE FROM amit.barak USING TIMESTAMP 84 WHERE dgqx='hti';"}, {"started_at": "2023-03-18T12:12:02.113000", "duration": "0:00:00.005520", "query": "DELETE FROM amit.barak USING TIMESTAMP 85 WHERE dgqx='tsk';"}, {"started_at": "2023-03-18T12:12:02.113000", "duration": "0:00:00.005681", "query": "DELETE FROM amit.barak USING TIMESTAMP 86 WHERE dgqx='caj';"}, {"started_at": "2023-03-18T12:12:02.121000", "duration": "0:00:00.011933", "query": "DELETE FROM amit.barak USING TIMESTAMP 87 WHERE dgqx='lpt';"}, {"started_at": "2023-03-18T12:12:02.121000", "duration": "0:00:00.011103", "query": "DELETE FROM amit.barak USING TIMESTAMP 88 WHERE dgqx='lra';"}, {"started_at": "2023-03-18T12:12:02.121000", "duration": "0:00:00.012397", "query": "DELETE FROM amit.barak USING TIMESTAMP 89 WHERE dgqx='zle';"}, {"started_at": "2023-03-18T12:12:02.121000", "duration": "0:00:00.011041", "query": "DELETE FROM amit.barak USING TIMESTAMP 90 WHERE dgqx='keh';"}, {"started_at": "2023-03-18T12:12:02.122000", "duration": "0:00:00.010679", "query": "DELETE FROM amit.barak USING TIMESTAMP 91 WHERE dgqx='hij';"}, {"started_at": "2023-03-18T12:12:02.122000", "duration": "0:00:00.011307", "query": "DELETE FROM amit.barak USING TIMESTAMP 92 WHERE dgqx='fyq';"}, {"started_at": "2023-03-18T12:12:02.122000", "duration": "0:00:00.010644", "query": "DELETE FROM amit.barak USING TIMESTAMP 93 WHERE dgqx='xly';"}, {"started_at": "2023-03-18T12:12:02.122000", "duration": "0:00:00.010442", "query": "DELETE FROM amit.barak USING TIMESTAMP 94 WHERE dgqx='xgy';"}, {"started_at": "2023-03-18T12:12:02.122000", "duration": "0:00:00.010613", "query": "DELETE FROM amit.barak USING TIMESTAMP 95 WHERE dgqx='uyf';"}, {"started_at": "2023-03-18T12:12:02.122000", "duration": "0:00:00.011666", "query": "DELETE FROM amit.barak USING TIMESTAMP 96 WHERE dgqx='msg';"}, {"started_at": "2023-03-18T12:12:02.147000", "duration": "0:00:00.007997", "query": "DELETE FROM amit.barak USING TIMESTAMP 97 WHERE dgqx='uwe';"}, {"started_at": "2023-03-18T12:12:02.147000", "duration": "0:00:00.008270", "query": "DELETE FROM amit.barak USING TIMESTAMP 98 WHERE dgqx='zlx';"}, {"started_at": "2023-03-18T12:12:02.149000", "duration": "0:00:00.006864", "query": "DELETE FROM amit.barak USING TIMESTAMP 99 WHERE dgqx='tnw';"}, {"started_at": "2023-03-18T12:12:02.149000", "duration": "0:00:00.006327", "query": "DELETE FROM amit.barak USING TIMESTAMP 100 WHERE dgqx='zsh';"}]